test.py
test.py.zipdep.py
test2.py
zipdep.py
zipdep.py-1.3.0.data/scripts/zipdep.py
zipdep.py-1.3.0.dist-info/DESCRIPTION.rst
zipdep.py-1.3.0.dist-info/METADATA
zipdep.py-1.3.0.dist-info/RECORD
zipdep.py-1.3.0.dist-info/WHEEL
zipdep.py-1.3.0.dist-info/metadata.json
zipdep.py-1.3.0.dist-info/top_level.txt
