Metadata-Version: 2.0
Name: zipdep.py
Version: 1.3.0
Summary: Packaging dependencies into your app
Home-page: https://git.veriny.tf/SunDwarf/zipdep.py
Author: Isaac Dickinson
Author-email: eyes@veriny.tf
License: MIT
Platform: UNKNOWN
